django_storage_celery_results/__init__.py
django_storage_celery_results/backends.py
django_storage_celery_results-0.0.2b1.dist-info/LICENSE
django_storage_celery_results-0.0.2b1.dist-info/METADATA
django_storage_celery_results-0.0.2b1.dist-info/WHEEL
django_storage_celery_results-0.0.2b1.dist-info/entry_points.txt
django_storage_celery_results-0.0.2b1.dist-info/top_level.txt
django_storage_celery_results-0.0.2b1.dist-info/RECORD
